haystack_memory-0.7.dist-info/METADATA
haystack_memory-0.7.dist-info/WHEEL
haystack_memory-0.7.dist-info/licenses/LICENSE
haystack_memory/__init__.py
haystack_memory/memory.py
haystack_memory/prompt_templates.py
haystack_memory/utils.py
haystack_memory-0.7.dist-info/RECORD
