Metadata-Version: 2.1
Name: haystack-memory
Version: 0.7
Summary: Memory library for Haystack NLP agents.
Author: Florian Brand <github@florianbrand.de>, Roland Tannous, Tuana Celik, recrudesce
License: MIT
Classifier: Programming Language :: Python :: 3
Classifier: License :: OSI Approved :: MIT License
Classifier: Operating System :: OS Independent
Project-URL: Homepage, https://github.com/rolandtannous/haystack-memory
Project-URL: Bug tracker, https://github.com/rolandtannous/haystack-memory/issues
Requires-Python: >=3.9.16
Requires-Dist: farm-haystack>=1.15.0
Requires-Dist: redis
